{
 "actions": [],
 "creation": "2021-01-09 16:12:04.314346",
 "doctype": "DocType",
 "editable_grid": 1,
 "engine": "InnoDB",
 "field_order": [
  "shift_type"
 ],
 "fields": [
  {
   "fieldname": "shift_type",
   "fieldtype": "Link",
   "in_list_view": 1,
   "label": "Shift Type",
   "options": "Shift Type",
   "reqd": 1
  }
 ],
 "index_web_pages_for_search": 1,
 "istable": 1,
 "links": [],
 "modified": "2021-01-09 16:12:04.314346",
 "modified_by": "Administrator",
 "module": "Essdee Attendance",
 "name": "Combined Shift Type",
 "owner": "Administrator",
 "permissions": [],
 "quick_entry": 1,
 "sort_field": "modified",
 "sort_order": "DESC",
 "track_changes": 1
}